{
"LogoID":"[data-testid=\"oud-logo-img\"]",
"SearchBarID":"[data-testid=\"search-input\"]",
"LoginButtonID":"[data-testid=\"login-btn\"]",
"SignUpButtonID":"[data-testid=\"signup-btn\"]",
"UpgradeButtonID":"[data-testid=\"upgrade-link\"]",
"ImgProfileID":"[data-testid=\"profile-img\"]",
"AccountButtonID":"[data-testid=\"account-dropdown-element\"]",
"LogoutButtonID":"[data-testid=\"logout-dropdown-element\"]",
"Toggle-barID":"data-testid=\"toggle-btn\"",
"PlaylistFirstHalfOfXpath":"//*[@id=\"root\"]/div/div[1]/section/section/div[",
"PlaylistMiddleHalfOfXpath":"]/div[2]/div/div/div[",
"PlaylistlastHalfOfXpath":"]/div/div[2]/a",
"SeeAllXpathFirstPart":"//*[@id=\"root\"]/div/div[1]/section/section/div[",
"SeeAllXpathSecondPart":"]/div[1]/a/div",
"ToggleButton":"[data-testid=\"toggle-btn\"]",
"UpgradButtonIDToggleButton":"[data-testid=\"upgrade-btn\"]",
"DropButtonXpath":"//*[@id=\"songDropdownButton\"]",
"AddToPlayListXpath":"//*[@id=\"dropdownContent\"]/button[3]",
"BackButtonXpath":"//*[@id=\"root\"]/div/div[1]/div[2]/nav/form/div/div[1]/i",
"ForwardButtonXpath":"//*[@id=\"root\"]/div/div[1]/div[2]/nav/form/div/div[2]/i"
}
